econf.py
python_libeconf-1.1.0.dist-info/LICENSE
python_libeconf-1.1.0.dist-info/METADATA
python_libeconf-1.1.0.dist-info/WHEEL
python_libeconf-1.1.0.dist-info/top_level.txt
python_libeconf-1.1.0.dist-info/RECORD
