Metadata-Version: 2.1
Name: python-libeconf
Version: 1.1.0
Summary: Python bindings for libeconf
Author-email: nkrapp <nico.krapp@suse.com>
License-File: LICENSE
Provides-Extra: doc_requires
Requires-Dist: sphinx ; extra == 'doc_requires'
Requires-Dist: sphinx-rtd-theme ; extra == 'doc_requires'
Provides-Extra: test_requires
Requires-Dist: pytest ; extra == 'test_requires'
